processing/__init__.py
processing/combination.py
processing/transformation.py
utils/__init__.py
utils/io.py
utils/plot.py
processamento_imagens_matheus-0.1.dist-info/LICENSE
processamento_imagens_matheus-0.1.dist-info/METADATA
processamento_imagens_matheus-0.1.dist-info/WHEEL
processamento_imagens_matheus-0.1.dist-info/top_level.txt
processamento_imagens_matheus-0.1.dist-info/RECORD
