Metadata-Version: 2.1
Name: processamento-imagens-matheus
Version: 0.1
Summary: Image processing package using Skimage
Home-page: https://github.com/mpizanii/package_imagens_python
Author: Matheus Pizani
Requires-Python: >=3.5
License-File: LICENSE
Requires-Dist: matplotlib
Requires-Dist: numpy
Requires-Dist: scikit-image>=0.16.1
